pylbmisc/__init__.py
pylbmisc/dm.py
pylbmisc/fig.py
pylbmisc/io.py
pylbmisc/iter.py
pylbmisc/py.typed
pylbmisc/r.py
pylbmisc/rand.py
pylbmisc/stats.py
pylbmisc/surv.py
pylbmisc/tg.py
pylbmisc/utils.py
pylbmisc/datasets/.RData
pylbmisc/datasets/Makefile
pylbmisc/datasets/SAheart.csv
pylbmisc/datasets/__init__.py
pylbmisc/datasets/aidssi.csv
pylbmisc/datasets/anorexia.csv
pylbmisc/datasets/arthritis.csv
pylbmisc/datasets/beetles1.csv
pylbmisc/datasets/beetles2.csv
pylbmisc/datasets/camellia.csv
pylbmisc/datasets/claims.csv
pylbmisc/datasets/compact.csv
pylbmisc/datasets/crimeFL.csv
pylbmisc/datasets/csv_gen.R
pylbmisc/datasets/csv_gen.Rout
pylbmisc/datasets/dae_ologit.csv
pylbmisc/datasets/ebmt3.csv
pylbmisc/datasets/film.csv
pylbmisc/datasets/fitness.csv
pylbmisc/datasets/frei.csv
pylbmisc/datasets/influences.csv
pylbmisc/datasets/laureati.csv
pylbmisc/datasets/libri.csv
pylbmisc/datasets/mental.csv
pylbmisc/datasets/metabcg.csv
pylbmisc/datasets/metabin.csv
pylbmisc/datasets/metacon.csv
pylbmisc/datasets/metacor.csv
pylbmisc/datasets/mros.csv
pylbmisc/datasets/msofa.csv
pylbmisc/datasets/ovarian.csv
pylbmisc/datasets/political.csv
pylbmisc/datasets/political2.csv
pylbmisc/datasets/produzione.csv
pylbmisc/datasets/prostate.csv
pylbmisc/datasets/prostate_orig.csv
pylbmisc/datasets/studenti.csv
pylbmisc-0.0.7.dist-info/METADATA
pylbmisc-0.0.7.dist-info/WHEEL
pylbmisc-0.0.7.dist-info/licenses/LICENSE.txt
pylbmisc-0.0.7.dist-info/RECORD
